houseofreps/__init__.py
houseofreps/apportionment.csv
houseofreps/house.py
houseofreps/min_pop_changes.py
houseofreps/population_shifts.py
houseofreps/state.py
houseofreps/validate.py
houseofreps-0.1.1.dist-info/LICENSE
houseofreps-0.1.1.dist-info/METADATA
houseofreps-0.1.1.dist-info/WHEEL
houseofreps-0.1.1.dist-info/top_level.txt
houseofreps-0.1.1.dist-info/RECORD
