Metadata-Version: 2.1
Name: houseofreps
Version: 0.1.1
Summary: Apportionment of representatives in U.S. House of Representatives.
Home-page: https://github.com/smrfeld/house-of-reps/
Author: smrfeld
Author-email: oliver.k.ernst@gmail.com
License: MIT
Classifier: Programming Language :: Python :: 3
Classifier: License :: OSI Approved :: MIT License
Classifier: Operating System :: OS Independent
Requires-Python: >=3.6
License-File: LICENSE
Requires-Dist: loguru
Requires-Dist: mashumaro
Requires-Dist: numpy
Requires-Dist: pandas
Requires-Dist: plotly
Requires-Dist: pytest
Requires-Dist: setuptools
Requires-Dist: tqdm
